coindata/__init__.py
coindata/cacher.py
coindata/parser.py
coindata/request.py
coindata/utils.py
coindata-1.4.dist-info/LICENSE
coindata-1.4.dist-info/METADATA
coindata-1.4.dist-info/WHEEL
coindata-1.4.dist-info/top_level.txt
coindata-1.4.dist-info/RECORD
