Metadata-Version: 2.1
Name: coindata
Version: 1.4
Summary: Historical data manager for cryptos.
Home-page: https://github.com/anaxilaus/coindata
Author: Anaxilaus
Author-email: UNKNOWN
License: UNKNOWN
Platform: UNKNOWN
Requires-Dist: requests (>=2.18.4)
Requires-Dist: beautifulsoup4 (>=4.6.0)
